PILTH/Get_Next_Task.py
PILTH/__init__.py
PILTH-0.0.2.dist-info/METADATA
PILTH-0.0.2.dist-info/WHEEL
PILTH-0.0.2.dist-info/top_level.txt
PILTH-0.0.2.dist-info/RECORD
